milvus/.DS_Store
milvus/__init__.py
milvus/data/config.yaml.template
milvus/data/glog.conf
milvus/data/bin/libblob-chunk-manager.dylib.lzma
milvus/data/bin/libgflags_nothreads.2.2.dylib.lzma
milvus/data/bin/libglog.1.dylib.lzma
milvus/data/bin/libknowhere.dylib.lzma
milvus/data/bin/libmilvus_common.dylib.lzma
milvus/data/bin/libmilvus_index.dylib.lzma
milvus/data/bin/libmilvus_indexbuilder.dylib.lzma
milvus/data/bin/libmilvus_segcore.dylib.lzma
milvus/data/bin/libmilvus_storage.dylib.lzma
milvus/data/bin/libomp.dylib.lzma
milvus/data/bin/librdkafka++.1.dylib.lzma
milvus/data/bin/librdkafka.1.dylib.lzma
milvus/data/bin/librocksdb.6.dylib.lzma
milvus/data/bin/libtbb.12.dylib.lzma
milvus/data/bin/libunwind.1.dylib.lzma
milvus/data/bin/milvus.lzma
milvus-2.3.9.dist-info/LICENSE
milvus-2.3.9.dist-info/METADATA
milvus-2.3.9.dist-info/WHEEL
milvus-2.3.9.dist-info/entry_points.txt
milvus-2.3.9.dist-info/top_level.txt
milvus-2.3.9.dist-info/RECORD
