Metadata-Version: 2.1
Name: milvus
Version: 2.3.9
Summary: Embeded Milvus
Home-page: https://github.com/milvus-io/milvus-lite
Author: Milvus Team
Author-email: milvus-team@zilliz.com
Maintainer: Ji Bin
Maintainer-email: matrixji@live.com
License: Apache-2.0
Keywords: Milvus,Embeded Milvus,Milvus Server
Requires-Python: >=3.6
License-File: LICENSE
Provides-Extra: client
Requires-Dist: pymilvus <2.4.0,>=2.3.0b1 ; extra == 'client'
